jms_oidc_rp/__init__.py
jms_oidc_rp/admin.py
jms_oidc_rp/apps.py
jms_oidc_rp/backends.py
jms_oidc_rp/context_processors.py
jms_oidc_rp/decorator.py
jms_oidc_rp/middleware.py
jms_oidc_rp/models.py
jms_oidc_rp/signals.py
jms_oidc_rp/urls.py
jms_oidc_rp/utils.py
jms_oidc_rp/views.py
jms_oidc_rp/conf/__init__.py
jms_oidc_rp/conf/settings.py
jms_oidc_rp/contrib/__init__.py
jms_oidc_rp/contrib/rest_framework/__init__.py
jms_oidc_rp/contrib/rest_framework/authentication.py
jms_oidc_rp/migrations/0001_initial.py
jms_oidc_rp/migrations/__init__.py
oidc_rp/__init__.py
oidc_rp/admin.py
oidc_rp/apps.py
oidc_rp/backends.py
oidc_rp/context_processors.py
oidc_rp/middleware.py
oidc_rp/models.py
oidc_rp/signals.py
oidc_rp/urls.py
oidc_rp/utils.py
oidc_rp/views.py
oidc_rp/conf/__init__.py
oidc_rp/conf/settings.py
oidc_rp/contrib/__init__.py
oidc_rp/contrib/rest_framework/__init__.py
oidc_rp/contrib/rest_framework/authentication.py
oidc_rp/migrations/0001_initial.py
oidc_rp/migrations/__init__.py
jumpserver_django_oidc_rp-0.3.7.8.dist-info/LICENSE
jumpserver_django_oidc_rp-0.3.7.8.dist-info/METADATA
jumpserver_django_oidc_rp-0.3.7.8.dist-info/WHEEL
jumpserver_django_oidc_rp-0.3.7.8.dist-info/top_level.txt
jumpserver_django_oidc_rp-0.3.7.8.dist-info/RECORD
